lcl_xhs_mcp-0.4.3.dist-info/licenses/LICENCE
xhs_mcp/__init__.py
xhs_mcp/image_generate.py
xhs_mcp/mcp_server.py
xhs_mcp/mcp_util.py
lcl_xhs_mcp-0.4.3.dist-info/METADATA
lcl_xhs_mcp-0.4.3.dist-info/WHEEL
lcl_xhs_mcp-0.4.3.dist-info/entry_points.txt
lcl_xhs_mcp-0.4.3.dist-info/top_level.txt
lcl_xhs_mcp-0.4.3.dist-info/RECORD
