Metadata-Version: 2.4
Name: lcl_xhs_mcp
Version: 0.4.3
Summary: A Model Context Protocol (MCP) server for Xiaohongshu (Little Red Book) automation
Project-URL: Homepage, https://github.com/SoftEgLi/xhs-mcp
Project-URL: Bug Reports, https://github.com/SoftEgLi/xhs-mcp/issues
Project-URL: Source, https://github.com/SoftEgLi/xhs-mcp
Classifier: Development Status :: 3 - Alpha
Classifier: Intended Audience :: Developers
Classifier: License :: OSI Approved :: MIT License
Classifier: Programming Language :: Python :: 3
Classifier: Programming Language :: Python :: 3.8
Classifier: Programming Language :: Python :: 3.9
Classifier: Programming Language :: Python :: 3.10
Classifier: Programming Language :: Python :: 3.11
Requires-Python: >=3.8
License-File: LICENCE
Requires-Dist: selenium
Requires-Dist: pyperclip
Requires-Dist: httpx
Requires-Dist: openai
Requires-Dist: html2image
Requires-Dist: fastmcp
Requires-Dist: webdriver-manager
Dynamic: license-file
